.gitignore
CHANGELOG.txt
LICENSE.txt
MANIFEST.in
README-BINARY-DEMOS.txt
README-DEMOS.txt
README.txt
bootstrap.py
build-demo-dir.py
build-win-exe-demos.py
buildout.cfg
check-config.py
makepimp.py
pyz_support.py
setup.py
update_docstrings.py
upload_to_pypi.sh
vc7.bat
VisionEgg/Configuration.py
VisionEgg/Core.py
VisionEgg/Daq.py
VisionEgg/DaqKeyboard.py
VisionEgg/DaqLPT.py
VisionEgg/Deprecated.py
VisionEgg/Dots.py
VisionEgg/FlowControl.py
VisionEgg/GL.py
VisionEgg/GLTrace.py
VisionEgg/GUI.py
VisionEgg/Gratings.py
VisionEgg/MoreStimuli.py
VisionEgg/ParameterTypes.py
VisionEgg/PlatformDependent.py
VisionEgg/PyroClient.py
VisionEgg/PyroHelpers.py
VisionEgg/QuickTime.py
VisionEgg/ResponseControl.py
VisionEgg/SphereMap.py
VisionEgg/TCPController.py
VisionEgg/Text.py
VisionEgg/Textures.py
VisionEgg/ThreeDeeMath.py
VisionEgg/VisionEgg.cfg
VisionEgg/WrappedText.py
VisionEgg/__init__.py
VisionEgg/_darwin_sync_swap.m
VisionEgg/_draw_in_c.c
VisionEgg/_lib3ds.c
VisionEgg/_raw_lpt_linux.c
VisionEgg/_raw_plp_irix.c
VisionEgg/_vegl.c
VisionEgg/_vegl.pyx
VisionEgg/darwin_getrefresh.m
VisionEgg/darwin_getrefresh.py
VisionEgg/darwin_getrefresh_wrap.c
VisionEgg/darwin_maxpriority.c
VisionEgg/darwin_maxpriority.pyx
VisionEgg/darwinsys.pxd
VisionEgg/darwinsys_compat.h
VisionEgg/gl_qt.c
VisionEgg/gl_qt.h
VisionEgg/gl_qt.py
VisionEgg/gl_qt_wrap.c
VisionEgg/movieconvert.c
VisionEgg/movieconvert.h
VisionEgg/posix_maxpriority.c
VisionEgg/posix_maxpriority.py
VisionEgg/posix_maxpriority_wrap.c
VisionEgg/qtlowlevel.py
VisionEgg/qtmovie.py
VisionEgg/test_Core.py
VisionEgg/vegl.h
VisionEgg/win32_getrefresh.c
VisionEgg/win32_getrefresh.py
VisionEgg/win32_getrefresh_wrap.c
VisionEgg/win32_load_driver.c
VisionEgg/win32_load_driver.h
VisionEgg/win32_maxpriority.c
VisionEgg/win32_maxpriority.py
VisionEgg/win32_maxpriority_wrap.c
VisionEgg/win32_vretrace.c
VisionEgg/win32_vretrace.pyx
VisionEgg/win32_vretrace_orig.h
VisionEgg/PyroApps/AST_ext.py
VisionEgg/PyroApps/ColorCalGUI.py
visionegg.egg-info/PKG-INFO
visionegg.egg-info/SOURCES.txt
visionegg.egg-info/dependency_links.txt
visionegg.egg-info/top_level.txt